ckanext_charts-1.8.0-py3.10-nspkg.pth
ckanext/charts/__init__.py
ckanext/charts/cache.py
ckanext/charts/config.py
ckanext/charts/config_declaration.yaml
ckanext/charts/config_schema.yaml
ckanext/charts/const.py
ckanext/charts/exception.py
ckanext/charts/fetchers.py
ckanext/charts/helpers.py
ckanext/charts/plugin.py
ckanext/charts/types.py
ckanext/charts/utils.py
ckanext/charts/views.py
ckanext/charts/assets/webassets.yml
ckanext/charts/assets/css/charts.css
ckanext/charts/assets/css/vendor/tom-select.min.css
ckanext/charts/assets/js/charts-filters.js
ckanext/charts/assets/js/charts-global.js
ckanext/charts/assets/js/charts-render-chartjs.js
ckanext/charts/assets/js/charts-render-echarts.js
ckanext/charts/assets/js/charts-render-observable.js
ckanext/charts/assets/js/charts-render-plotly.js
ckanext/charts/assets/js/charts-select.js
ckanext/charts/assets/js/vendor/chartjs-adapter-moment.js
ckanext/charts/assets/js/vendor/chartjs-plugin-zoom.min.js
ckanext/charts/assets/js/vendor/chartjs.min.js
ckanext/charts/assets/js/vendor/d3.min.js
ckanext/charts/assets/js/vendor/echarts.min.js
ckanext/charts/assets/js/vendor/hammerjs.min.js
ckanext/charts/assets/js/vendor/htmx.min.js
ckanext/charts/assets/js/vendor/jsoneditor.min.js
ckanext/charts/assets/js/vendor/observable.min.js
ckanext/charts/assets/js/vendor/plotly.min.js
ckanext/charts/assets/js/vendor/tom-select.complete.min.js
ckanext/charts/chart_builders/__init__.py
ckanext/charts/chart_builders/base.py
ckanext/charts/chart_builders/chartjs.py
ckanext/charts/chart_builders/observable.py
ckanext/charts/chart_builders/echarts/__init__.py
ckanext/charts/chart_builders/echarts/bar.py
ckanext/charts/chart_builders/echarts/base.py
ckanext/charts/chart_builders/echarts/line.py
ckanext/charts/chart_builders/echarts/pie.py
ckanext/charts/chart_builders/plotly/__init__.py
ckanext/charts/chart_builders/plotly/bar.py
ckanext/charts/chart_builders/plotly/base.py
ckanext/charts/chart_builders/plotly/choropleth.py
ckanext_charts-1.8.0.dist-info/licenses/LICENSE
ckanext_charts-1.8.0.dist-info/METADATA
ckanext_charts-1.8.0.dist-info/WHEEL
ckanext_charts-1.8.0.dist-info/entry_points.txt
ckanext_charts-1.8.0.dist-info/namespace_packages.txt
ckanext_charts-1.8.0.dist-info/top_level.txt
ckanext_charts-1.8.0.dist-info/RECORD
