Metadata-Version: 2.4
Name: ckanext-charts
Version: 1.8.0
Author-email: DataShades <datashades@linkdigital.com.au>, Sergey Motornyuk <sergey.motornyuk@linkdigital.com.au>, Oleksandr Cherniavskyi <mutantsan@gmail.com>
Maintainer-email: DataShades <datashades@linkdigital.com.au>
License: AGPL
Project-URL: Homepage, https://github.com/DataShades/ckanext-charts
Keywords: CKAN,charts,visualization
Classifier: Development Status :: 4 - Beta
Classifier: License :: OSI Approved :: GNU Affero General Public License v3 or later (AGPLv3+)
Classifier: Programming Language :: Python
Classifier: Programming Language :: Python :: 3.10
Classifier: Programming Language :: Python :: 3.11
Classifier: Programming Language :: Python :: 3.12
Classifier: Programming Language :: Python :: 3.9
Classifier: Programming Language :: Python :: 3.8
Requires-Python: >=3.8
License-File: LICENSE
Requires-Dist: typing-extensions>=4.3.0
Requires-Dist: pandas<=2.1.4,>=2.0.0
Requires-Dist: plotly<6.0.0,>=5.21.0
Requires-Dist: redis<6.0.0,>=5.0.0
Requires-Dist: openpyxl<4.0.0,>=3.1.2
Requires-Dist: xlrd<3.0.0,>=2.0.1
Requires-Dist: humanize<5.0.0,>=4.10.0
Requires-Dist: pycountry<25.0.0,>=24.6.1
Requires-Dist: ckanext-scheming
Provides-Extra: pyarrow
Requires-Dist: pyarrow<17.0.0,>=16.0.0; extra == "pyarrow"
Provides-Extra: test
Requires-Dist: pytest-ckan; extra == "test"
Requires-Dist: ckanext-toolbelt; extra == "test"
Requires-Dist: requests-mock; extra == "test"
Provides-Extra: dev
Requires-Dist: pytest-ckan; extra == "dev"
Requires-Dist: ckanext-toolbelt; extra == "dev"
Requires-Dist: requests-mock; extra == "dev"
Provides-Extra: docs
Requires-Dist: mkdocs; extra == "docs"
Requires-Dist: mkdocs-material; extra == "docs"
Requires-Dist: mkdocstrings; extra == "docs"
Requires-Dist: mkdocstrings-python; extra == "docs"
Requires-Dist: pymdown-extensions; extra == "docs"
Dynamic: license-file
